pyphoton/__init__.py
pyphoton/client.py
pyphoton/errors.py
pyphoton/models.py
pyphoton-1.0.0.dist-info/LICENSE
pyphoton-1.0.0.dist-info/METADATA
pyphoton-1.0.0.dist-info/WHEEL
pyphoton-1.0.0.dist-info/top_level.txt
pyphoton-1.0.0.dist-info/RECORD
