Metadata-Version: 2.1
Name: pyphoton
Version: 1.0.0
Summary: Photon Python client
Home-page: https://github.com/astagi/pyphoton
Author: Andrea Stagi
Author-email: stagi.andrea@gmail.com
License: MIT
Platform: UNKNOWN
Classifier: Environment :: Web Environment
Classifier: Intended Audience :: Developers
Classifier: Programming Language :: Python
Classifier: Programming Language :: Python :: 3
License-File: LICENSE
Requires-Dist: requests (==2.26.0)
